README.md
setup.py
pydob/__init__.py
pydob.egg-info/PKG-INFO
pydob.egg-info/SOURCES.txt
pydob.egg-info/dependency_links.txt
pydob.egg-info/top_level.txt
pydob/db/__init__.py
pydob/db/table.py
pydob/types/__init__.py
pydob/types/lists.py
pydob/types/maps.py
pydob/types/types.py