Metadata-Version: 2.1
Name: pydob
Version: 0.0.2
Summary: PyDOB  connector
Home-page: https://github.com/pranavbaburaj/
Author: Pranav Baburaj
License: UNKNOWN
Platform: UNKNOWN
Classifier: Programming Language :: Python :: 3
Classifier: License :: OSI Approved :: MIT License
Classifier: Operating System :: OS Independent
Requires-Python: >=3.6
